SamPytorchHelper/TorchHelper.py
SamPytorchHelper/__init__.py
SamPytorchHelper-0.1.0.dist-info/LICENSE
SamPytorchHelper-0.1.0.dist-info/METADATA
SamPytorchHelper-0.1.0.dist-info/WHEEL
SamPytorchHelper-0.1.0.dist-info/top_level.txt
SamPytorchHelper-0.1.0.dist-info/RECORD
