Metadata-Version: 2.1
Name: SamPytorchHelper
Version: 0.1.0
Summary: Make pytorch implementation easy, so that one can focus on what is really important!!!!
Home-page: https://github.com/sams500/SamPytorchHelper
Author: Soilihi Abderemane
Author-email: Abderemane500@gmail.com
License: UNKNOWN
Project-URL: Bug Tracker, https://github.com/sams500/SamPytorchHelper/issues
Platform: UNKNOWN
Classifier: Programming Language :: Python :: 3
Classifier: License :: OSI Approved :: MIT License
Classifier: Operating System :: OS Independent
Requires-Python: >=3.6
License-File: LICENSE
